SaGaF_info/SaGaF_info.py
SaGaF_info/__init__.py
SaGaF_info-0.1.dist-info/LICENSE
SaGaF_info-0.1.dist-info/METADATA
SaGaF_info-0.1.dist-info/WHEEL
SaGaF_info-0.1.dist-info/top_level.txt
SaGaF_info-0.1.dist-info/RECORD
